out_and_in/__init__.py
out_and_in/demo.py
out_and_in/main.py
out_and_in-1.1.dist-info/METADATA
out_and_in-1.1.dist-info/WHEEL
out_and_in-1.1.dist-info/top_level.txt
out_and_in-1.1.dist-info/RECORD
