Metadata-Version: 2.1
Name: out-and-in
Version: 1.1
Summary: a backward feature elimination followed with forwared features selection strategy. 
Home-page: https://github.com/chenfengMeng2021/out_and_in
Author: chenfeng Meng
Author-email: chenfengmeng0@gmail.com
License: MIT
Classifier: Programming Language :: Python :: 3
Classifier: License :: OSI Approved :: MIT License
Requires-Dist: pandas ==2.0.3
Requires-Dist: scikit-learn ==1.3.0
Requires-Dist: tqdm ==4.65.0
